einteract/__init__.py
einteract/__version__.py
einteract-1.4.3.dist-info/LICENSE
einteract-1.4.3.dist-info/METADATA
einteract-1.4.3.dist-info/WHEEL
einteract-1.4.3.dist-info/entry_points.txt
einteract-1.4.3.dist-info/top_level.txt
einteract-1.4.3.dist-info/RECORD
