Metadata-Version: 2.1
Name: einteract
Version: 1.4.3
Summary: An enhanced version of ipywidgets's interactive widgets.
Home-page: https://github.com/asaboor-gh/einteract
Author: Abdul Saboor
Author-email: asaboor.my@outlook.com
License: MIT
Project-URL: Bug Tracker, https://github.com/asaboor-gh/einteract/issues
Keywords: Jupyter,Widgets,IPython,interact,interactive
Platform: UNKNOWN
Classifier: License :: OSI Approved :: MIT License
Classifier: Programming Language :: Python :: 3
Classifier: Operating System :: OS Independent
Requires-Python: >=3.9
License-File: LICENSE
Requires-Dist: dashlab
Provides-Extra: extra
